Rx_/uart_rx.v
module uart_rx(
    input wire clk,
    input wire rst_n,
    input wire en,
    input wire rx_line,
    input wire baud_tick_16x,

    output reg rx_busy,
    output reg rx_done,
    output reg [7:0] data_received

);
reg [2:0] nstate, pstate;
reg [3:0] bit_count;
reg [3:0] baud_count;
reg [7:0] rx_shift_reg;

parameter [2:0] IDLE          = 3'b000,
                Enable        = 3'b001,
                Conf_rsv      = 3'b010,
                Receiving    = 3'b011,
                Receive_done  = 3'b100;

always @(*) begin: NSEQL //Non Sequential Logic
    begin:NSL //Next State Logic 
        case (pstate)
            IDLE: nstate = en ? Enable : IDLE;
            
            Enable: nstate = (!rx_line) ? Conf_rsv : Enable;  

            Conf_rsv: nstate = (baud_count == 4'd7) ? ((!rx_line) ? Receiving : Enable) : Conf_rsv;

            Receiving: nstate = (bit_count == 4'd8) ? Receive_done : Receiving;

            Receive_done: nstate = (!rx_line) ? Conf_rsv : Receive_done;

            default: nstate = IDLE;
        endcase
    end//end NSL

    begin: OL // Output logic
        case (pstate)
            IDLE: begin
                rx_busy = 1'b0;
                rx_done = 1'b0;
                data_received = 8'b0; // reset data received
                bit_count = 3'b0; // reset bit count
                baud_count = 4'b0; // reset baud count
            end 

            Enable: begin
                rx_busy = 1'b0;
                rx_done = 1'b0;
                data_received = 8'b0; // reset data received
                bit_count = 3'b0; // reset bit count
                baud_count = 4'b0; // reset baud count
            end

            Conf_rsv: begin 
                rx_busy = 1'b0;
                rx_done = 1'b0;
                //data_received = 8'b0;
                bit_count = 3'b0;
                if(baud_count >= 4'd7) begin 
                    baud_count = 4'b0;
                end
            end

            Receiving: begin 
                rx_busy = 1'b1;
                rx_done = 1'b0;
                data_received = 8'b0;
            end

            Receive_done: begin 
                rx_busy = 1'b0;
                rx_done = 1'b1;
                data_received = rx_shift_reg; // output the received data
                bit_count = 3'b0; // reset bit count
                baud_count = 4'b0; // reset baud count
            end
              
            default: begin 
                rx_busy <= 1'b0;
                rx_done <= 1'b0;
                data_received <= 8'b0; // reset data received
                bit_count <= 3'b0; // reset bit count
                baud_count <= 4'b0; // reset baud count
            end 
        endcase
    end//end OL
end //end NSEQL

always @(posedge clk, negedge rst_n) begin: SL // sequential logic
    if (!rst_n) begin
        pstate <= IDLE;
    end else begin
        if(pstate == Conf_rsv && baud_tick_16x) begin 
            baud_count <= baud_count + 1'b1;
        end
        if(pstate == Receiving && baud_tick_16x) begin 
            baud_count <= baud_count + 1'b1;
            if (baud_count == 4'd15) begin 
                baud_count <= 4'b0;
                bit_count <= bit_count + 1'b1;
                rx_shift_reg <= {rx_line, rx_shift_reg[7:1]};
            end
        end

        pstate <= nstate;
    end
end //end SL

endmodule

baud_gen.v
module baud_gen (
    input wire clk, 
    input wire rst_n,
    input wire cnt_1x,
    input wire cnt_16x,

    output reg clr,
    output reg baud_tick_1x,
    output reg baud_tick_16x

);

reg [1:0] nstate, pstate;

parameter [1:0]     IDLE         = 2'b00,
                    running      = 2'b01,
                    tick_16x     = 2'b10,
                    tick_1x      = 2'b11;

always @(*) begin: NSEQL // Non Sequential Logic
    begin: NSL // Next state Logic
        case(pstate) 
            IDLE    : nstate = (rst_n ? running : IDLE);
        
            running : nstate = (cnt_1x  ? tick_1x  : (cnt_16x ? tick_16x : running));
            
            tick_16x: nstate = running;

            tick_1x : nstate = running;

            default : nstate = IDLE;
            
        endcase

    end

    begin: OL // Output Logic  
        case(pstate) 
            IDLE    : begin 
                        clr = 1'b1;
                        baud_tick_16x = 1'b0;
                        baud_tick_1x = 1'b0;
            end
            running : begin 
                        clr = 1'b0;
                        baud_tick_16x = 1'b0;
                        baud_tick_1x = 1'b0;
            end
            tick_16x: begin 
                        clr = cnt_1x ? 1'b1 : 1'b0;
                        baud_tick_16x = 1'b1;
                        baud_tick_1x  = cnt_1x ? 1'b1 : 1'b0;
            end
            tick_1x : begin 
                        clr = 1'b1;
                        baud_tick_16x = 1'b1;
                        baud_tick_1x  = 1'b1;
            end
            default : begin 

            end
        endcase
    end

end

always @(posedge clk, negedge rst_n) begin : SEQL // sequential Logic
    if(~rst_n) begin 
        pstate <= IDLE;
    end
    else begin 
        pstate <= nstate;
    end
end

endmodule

count_comp/comparator.v
module comparator (
    input wire [15:0] count,
    input wire [15:0] baud_div,

    output wire cnt_16x,
    output wire cnt_1x
);
    wire[15:0] step_16x = baud_div >> 4;
    //reg [3:0] baud_count;
    assign cnt_1x = (count == baud_div-1) ? 1'b1 : 1'b0;
    assign cnt_16x = ((step_16x !=0) && ((count % step_16x)==0))? 1'b1 : 1'b0;

endmodule

count_comp/counter.v
module counter (
    input wire clk,
    input wire rst_n,
    input wire clr,

    output reg [15:0] count
);

always @(posedge clk, negedge rst_n) begin
    if(~rst_n) begin 
        count <= 16'd0;
    end
    else begin 
        count <= clr ? 16'd0 : count + 1;
    end
    
end
    
endmodule

Rx_/tb_rx.v
`timescale  1ns/1ps

module tb_rx;
//clock and reset
reg clk = 0;
reg rst_n;

//counter
wire clr;
wire [15:0] count;

//comparator
reg [15:0] baud_div = 16'd32;
wire cnt_16x;
wire cnt_1x;

//baud gen
wire baud_tick_16x;
wire baud_tick_1x;

//uart_rx
reg en;
reg rx_line;
wire rx_busy;
wire rx_done;
wire [7:0] data_received;

counter uut_counter (
    .clk(clk),
    .rst_n(rst_n),
    .clr(clr),
    .count(count)
);

comparator uut_comparator (
    .baud_div(baud_div),
    .count(count),
    .cnt_16x(cnt_16x),
    .cnt_1x(cnt_1x)
);

baud_gen uut_baud_gen (
    .clk(clk),
    .rst_n(rst_n),
    .cnt_1x(cnt_1x),
    .cnt_16x(cnt_16x),
    .clr(clr),
    .baud_tick_1x(baud_tick_1x),
    .baud_tick_16x(baud_tick_16x)
);

uart_rx uut_uart_rx (
    .clk(clk),
    .rst_n(rst_n),
    .en(en),
    .rx_line(rx_line),
    .baud_tick_16x(baud_tick_16x),
    .rx_busy(rx_busy),
    .rx_done(rx_done),
    .data_received(data_received)
);

always #5 clk = ~clk; // 100 MHz clock

// task to send a byte to the Uart receiver
task send_byte(input [7:0] byte);
    integer i;
    begin 
        //Start bit
        rx_line = 1'b0;
        repeat(16)@(posedge baud_tick_16x);

        //Sending data
        for( i =0; i<8; i++)begin 
            rx_line = byte[i];
            repeat(16)@(posedge baud_tick_16x);
        end

        //sending stop bit

        rx_line =  1'b1;
        repeat(16)@(posedge baud_tick_16x);
    end
endtask

initial begin
    $dumpfile("tb_rx.vcd");
    $dumpvars(0, tb_rx);

    rst_n = 1'b0;
    en = 1'b0;
    rx_line = 1'b1; // idle state of RX line
    @(posedge clk);

    rst_n <= 1'b1; // release reset
    repeat(2)@(posedge clk);
    en <= 1'b1; // enable UART receiver
    repeat(10)@(posedge clk);

    send_byte(8'hAA);
    repeat(170)@(posedge clk); // wait for some time

    send_byte(8'hAB);
    repeat(170)@(posedge clk);

    $finish; // end simulation

end

endmodule

tb_rx.vcd
$date
	Mon Jul 07 22:21:18 2025
$end
$version
	Icarus Verilog
$end
$timescale
	1ps
$end
$scope module tb_rx $end
$var wire 1 ! rx_done $end
$var wire 1 " rx_busy $end
$var wire 8 # data_received [7:0] $end
$var wire 16 $ count [15:0] $end
$var wire 1 % cnt_1x $end
$var wire 1 & cnt_16x $end
$var wire 1 ' clr $end
$var wire 1 ( baud_tick_1x $end
$var wire 1 ) baud_tick_16x $end
$var reg 16 * baud_div [15:0] $end
$var reg 1 + clk $end
$var reg 1 , en $end
$var reg 1 - rst_n $end
$var reg 1 . rx_line $end
$scope module uut_baud_gen $end
$var wire 1 + clk $end
$var wire 1 - rst_n $end
$var wire 1 % cnt_1x $end
$var wire 1 & cnt_16x $end
$var parameter 2 / IDLE $end
$var parameter 2 0 running $end
$var parameter 2 1 tick_16x $end
$var parameter 2 2 tick_1x $end
$var reg 1 ) baud_tick_16x $end
$var reg 1 ( baud_tick_1x $end
$var reg 1 ' clr $end
$var reg 2 3 nstate [1:0] $end
$var reg 2 4 pstate [1:0] $end
$scope begin NSEQL $end
$scope begin NSL $end
$upscope $end
$scope begin OL $end
$upscope $end
$upscope $end
$scope begin SEQL $end
$upscope $end
$upscope $end
$scope module uut_comparator $end
$var wire 16 5 baud_div [15:0] $end
$var wire 16 6 step_16x [15:0] $end
$var wire 16 7 count [15:0] $end
$var wire 1 % cnt_1x $end
$var wire 1 & cnt_16x $end
$upscope $end
$scope module uut_counter $end
$var wire 1 + clk $end
$var wire 1 ' clr $end
$var wire 1 - rst_n $end
$var reg 16 8 count [15:0] $end
$upscope $end
$scope module uut_uart_rx $end
$var wire 1 ) baud_tick_16x $end
$var wire 1 + clk $end
$var wire 1 , en $end
$var wire 1 - rst_n $end
$var wire 1 . rx_line $end
$var parameter 3 9 Conf_rsv $end
$var parameter 3 : Enable $end
$var parameter 3 ; IDLE $end
$var parameter 3 < Receive_done $end
$var parameter 3 = Receiving $end
$var reg 4 > baud_count [3:0] $end
$var reg 4 ? bit_count [3:0] $end
$var reg 8 @ data_received [7:0] $end
$var reg 3 A nstate [2:0] $end
$var reg 3 B pstate [2:0] $end
$var reg 1 " rx_busy $end
$var reg 1 ! rx_done $end
$var reg 8 C rx_shift_reg [7:0] $end
$scope begin NSEQL $end
$scope begin NSL $end
$upscope $end
$scope begin OL $end
$upscope $end
$upscope $end
$scope begin SL $end
$upscope $end
$upscope $end
$scope task send_byte $end
$var reg 8 D byte [7:0] $end
$var integer 32 E i [31:0] $end
$upscope $end
$upscope $end
$enddefinitions $end
$comment Show the parameter values. $end
$dumpall
b11 =
b100 <
b0 ;
b1 :
b10 9
b11 2
b10 1
b1 0
b0 /
$end
#0
$dumpvars
bx E
bx D
bx C
b0 B
b0 A
b0 @
b0 ?
b0 >
b0 8
b0 7
b10 6
b100000 5
b0 4
b0 3
1.
0-
0,
0+
b100000 *
0)
0(
1'
1&
0%
b0 $
b0 #
0"
0!
$end
#5000
b1 3
1-
1+
#10000
0+
#15000
0'
b10 3
b1 4
1+
#20000
0+
#25000
0&
1)
b1 3
b1 A
b10 4
b1 $
b1 7
b1 8
1,
1+
#30000
0+
#35000
b10 3
1&
0)
b1 B
b1 4
b10 $
b10 7
b10 8
1+
#40000
0+
#45000
0&
1)
b1 3
b10 4
b11 $
b11 7
b11 8
1+
#50000
0+
#55000
b10 3
1&
0)
b1 4
b100 $
b100 7
b100 8
1+
#60000
0+
#65000
0&
1)
b1 3
b10 4
b101 $
b101 7
b101 8
1+
#70000
0+
#75000
b10 3
1&
0)
b1 4
b110 $
b110 7
b110 8
1+
#80000
0+
#85000
0&
1)
b1 3
b10 4
b111 $
b111 7
b111 8
1+
#90000
0+
#95000
b10 3
1&
0)
b1 4
b1000 $
b1000 7
b1000 8
1+
#100000
0+
#105000
0&
1)
b1 3
b10 4
b1001 $
b1001 7
b1001 8
1+
#110000
0+
#115000
b10 3
1&
0)
b1 4
b1010 $
b1010 7
b1010 8
1+
#120000
0+
#125000
0&
1)
b1 3
b10 4
b1011 $
b1011 7
b1011 8
b10 A
0.
b10101010 D
1+
#130000
0+
#135000
b10 3
1&
0)
b10 B
b1 4
b1100 $
b1100 7
b1100 8
1+
#140000
0+
#145000
0&
1)
b1 3
b10 4
b1101 $
b1101 7
b1101 8
1+
#150000
0+
#155000
b10 3
1&
0)
b1 >
b1 4
b1110 $
b1110 7
b1110 8
1+
#160000
0+
#165000
0&
1)
b1 3
b10 4
b1111 $
b1111 7
b1111 8
1+
#170000
0+
#175000
b10 3
1&
0)
b10 >
b1 4
b10000 $
b10000 7
b10000 8
1+
#180000
0+
#185000
0&
1)
b1 3
b10 4
b10001 $
b10001 7
b10001 8
1+
#190000
0+
#195000
b10 3
1&
0)
b11 >
b1 4
b10010 $
b10010 7
b10010 8
1+
#200000
0+
#205000
0&
1)
b1 3
b10 4
b10011 $
b10011 7
b10011 8
1+
#210000
0+
#215000
b10 3
1&
0)
b100 >
b1 4
b10100 $
b10100 7
b10100 8
1+
#220000
0+
#225000
0&
1)
b1 3
b10 4
b10101 $
b10101 7
b10101 8
1+
#230000
0+
#235000
b10 3
1&
0)
b101 >
b1 4
b10110 $
b10110 7
b10110 8
1+
#240000
0+
#245000
0&
1)
b1 3
b10 4
b10111 $
b10111 7
b10111 8
1+
#250000
0+
#255000
b10 3
1&
0)
b110 >
b1 4
b11000 $
b11000 7
b11000 8
1+
#260000
0+
#265000
0&
1)
b1 3
b10 4
b11001 $
b11001 7
b11001 8
1+
#270000
0+
#275000
b10 3
1&
b11 A
0)
b0 >
b1 4
b11010 $
b11010 7
b11010 8
1+
#280000
0+
#285000
0&
1"
1)
b1 3
b11 B
b10 4
b11011 $
b11011 7
b11011 8
1+
#290000
0+
#295000
b10 3
1&
0)
b1 >
b1 4
b11100 $
b11100 7
b11100 8
1+
#300000
0+
#305000
0&
1)
b1 3
b10 4
b11101 $
b11101 7
b11101 8
1+
#310000
0+
#315000
b10 3
1&
0)
b10 >
b1 4
b11110 $
b11110 7
b11110 8
1+
#320000
0+
#325000
0&
1(
1)
1'
b1 3
1%
b10 4
b11111 $
b11111 7
b11111 8
1+
#330000
0+
#335000
b10 3
1&
0(
0)
0'
0%
b11 >
b1 4
b0 $
b0 7
b0 8
1+
#340000
0+
#345000
0&
1)
b1 3
b10 4
b1 $
b1 7
b1 8
1+
#350000
0+
#355000
b10 3
1&
0)
b100 >
b1 4
b10 $
b10 7
b10 8
1+
#360000
0+
#365000
0&
1)
b1 3
b10 4
b11 $
b11 7
b11 8
1+
#370000
0+
#375000
b10 3
1&
0)
b101 >
b1 4
b100 $
b100 7
b100 8
1+
#380000
0+
#385000
0&
1)
b1 3
b10 4
b101 $
b101 7
b101 8
1+
#390000
0+
#395000
b10 3
1&
0)
b110 >
b1 4
b110 $
b110 7
b110 8
1+
#400000
0+
#405000
0&
1)
b1 3
b10 4
b111 $
b111 7
b111 8
1+
#410000
0+
#415000
b10 3
1&
0)
b111 >
b1 4
b1000 $
b1000 7
b1000 8
1+
#420000
0+
#425000
b0 E
0&
1)
b1 3
b10 4
b1001 $
b1001 7
b1001 8
1+
#430000
0+
#435000
b10 3
1&
0)
b1000 >
b1 4
b1010 $
b1010 7
b1010 8
1+
#440000
0+
#445000
0&
1)
b1 3
b10 4
b1011 $
b1011 7
b1011 8
1+
#450000
0+
#455000
b10 3
1&
0)
b1001 >
b1 4
b1100 $
b1100 7
b1100 8
1+
#460000
0+
#465000
0&
1)
b1 3
b10 4
b1101 $
b1101 7
b1101 8
1+
#470000
0+
#475000
b10 3
1&
0)
b1010 >
b1 4
b1110 $
b1110 7
b1110 8
1+
#480000
0+
#485000
0&
1)
b1 3
b10 4
b1111 $
b1111 7
b1111 8
1+
#490000
0+
#495000
b10 3
1&
0)
b1011 >
b1 4
b10000 $
b10000 7
b10000 8
1+
#500000
0+
#505000
0&
1)
b1 3
b10 4
b10001 $
b10001 7
b10001 8
1+
#510000
0+
#515000
b10 3
1&
0)
b1100 >
b1 4
b10010 $
b10010 7
b10010 8
1+
#520000
0+
#525000
0&
1)
b1 3
b10 4
b10011 $
b10011 7
b10011 8
1+
#530000
0+
#535000
b10 3
1&
0)
b1101 >
b1 4
b10100 $
b10100 7
b10100 8
1+
#540000
0+
#545000
0&
1)
b1 3
b10 4
b10101 $
b10101 7
b10101 8
1+
#550000
0+
#555000
b10 3
1&
0)
b1110 >
b1 4
b10110 $
b10110 7
b10110 8
1+
#560000
0+
#565000
0&
1)
b1 3
b10 4
b10111 $
b10111 7
b10111 8
1+
#570000
0+
#575000
b10 3
1&
0)
b1111 >
b1 4
b11000 $
b11000 7
b11000 8
1+
#580000
0+
#585000
0&
1)
b1 3
b10 4
b11001 $
b11001 7
b11001 8
1+
#590000
0+
#595000
b10 3
1&
0)
b0xxxxxxx C
b1 ?
b0 >
b1 4
b11010 $
b11010 7
b11010 8
1+
#600000
0+
#605000
0&
1)
b1 3
b10 4
b11011 $
b11011 7
b11011 8
1+
#610000
0+
#615000
b10 3
1&
0)
b1 >
b1 4
b11100 $
b11100 7
b11100 8
1+
#620000
0+
#625000
0&
1)
b1 3
b10 4
b11101 $
b11101 7
b11101 8
1+
#630000
0+
#635000
b10 3
1&
0)
b10 >
b1 4
b11110 $
b11110 7
b11110 8
1+
#640000
0+
#645000
0&
1(
1)
1'
b1 3
1%
b10 4
b11111 $
b11111 7
b11111 8
1+
#650000
0+
#655000
b10 3
1&
0(
0)
0'
0%
b11 >
b1 4
b0 $
b0 7
b0 8
1+
#660000
0+
#665000
0&
1)
b1 3
b10 4
b1 $
b1 7
b1 8
1+
#670000
0+
#675000
b10 3
1&
0)
b100 >
b1 4
b10 $
b10 7
b10 8
1+
#680000
0+
#685000
0&
1)
b1 3
b10 4
b11 $
b11 7
b11 8
1+
#690000
0+
#695000
b10 3
1&
0)
b101 >
b1 4
b100 $
b100 7
b100 8
1+
#700000
0+
#705000
0&
1)
b1 3
b10 4
b101 $
b101 7
b101 8
1+
#710000
0+
#715000
b10 3
1&
0)
b110 >
b1 4
b110 $
b110 7
b110 8
1+
#720000
0+
#725000
0&
1)
b1 3
b10 4
b111 $
b111 7
b111 8
1+
#730000
0+
#735000
b10 3
1&
0)
b111 >
b1 4
b1000 $
b1000 7
b1000 8
1+
#740000
0+
#745000
1.
b1 E
0&
1)
b1 3
b10 4
b1001 $
b1001 7
b1001 8
1+
#750000
0+
#755000
b10 3
1&
0)
b1000 >
b1 4
b1010 $
b1010 7
b1010 8
1+
#760000
0+
#765000
0&
1)
b1 3
b10 4
b1011 $
b1011 7
b1011 8
1+
#770000
0+
#775000
b10 3
1&
0)
b1001 >
b1 4
b1100 $
b1100 7
b1100 8
1+
#780000
0+
#785000
0&
1)
b1 3
b10 4
b1101 $
b1101 7
b1101 8
1+
#790000
0+
#795000
b10 3
1&
0)
b1010 >
b1 4
b1110 $
b1110 7
b1110 8
1+
#800000
0+
#805000
0&
1)
b1 3
b10 4
b1111 $
b1111 7
b1111 8
1+
#810000
0+
#815000
b10 3
1&
0)
b1011 >
b1 4
b10000 $
b10000 7
b10000 8
1+
#820000
0+
#825000
0&
1)
b1 3
b10 4
b10001 $
b10001 7
b10001 8
1+
#830000
0+
#835000
b10 3
1&
0)
b1100 >
b1 4
b10010 $
b10010 7
b10010 8
1+
#840000
0+
#845000
0&
1)
b1 3
b10 4
b10011 $
b10011 7
b10011 8
1+
#850000
0+
#855000
b10 3
1&
0)
b1101 >
b1 4
b10100 $
b10100 7
b10100 8
1+
#860000
0+
#865000
0&
1)
b1 3
b10 4
b10101 $
b10101 7
b10101 8
1+
#870000
0+
#875000
b10 3
1&
0)
b1110 >
b1 4
b10110 $
b10110 7
b10110 8
1+
#880000
0+
#885000
0&
1)
b1 3
b10 4
b10111 $
b10111 7
b10111 8
1+
#890000
0+
#895000
b10 3
1&
0)
b1111 >
b1 4
b11000 $
b11000 7
b11000 8
1+
#900000
0+
#905000
0&
1)
b1 3
b10 4
b11001 $
b11001 7
b11001 8
1+
#910000
0+
#915000
b10 3
1&
0)
b10xxxxxx C
b10 ?
b0 >
b1 4
b11010 $
b11010 7
b11010 8
1+
#920000
0+
#925000
0&
1)
b1 3
b10 4
b11011 $
b11011 7
b11011 8
1+
#930000
0+
#935000
b10 3
1&
0)
b1 >
b1 4
b11100 $
b11100 7
b11100 8
1+
#940000
0+
#945000
0&
1)
b1 3
b10 4
b11101 $
b11101 7
b11101 8
1+
#950000
0+
#955000
b10 3
1&
0)
b10 >
b1 4
b11110 $
b11110 7
b11110 8
1+
#960000
0+
#965000
0&
1(
1)
1'
b1 3
1%
b10 4
b11111 $
b11111 7
b11111 8
1+
#970000
0+
#975000
b10 3
1&
0(
0)
0'
0%
b11 >
b1 4
b0 $
b0 7
b0 8
1+
#980000
0+
#985000
0&
1)
b1 3
b10 4
b1 $
b1 7
b1 8
1+
#990000
0+
#995000
b10 3
1&
0)
b100 >
b1 4
b10 $
b10 7
b10 8
1+
#1000000
0+
#1005000
0&
1)
b1 3
b10 4
b11 $
b11 7
b11 8
1+
#1010000
0+
#1015000
b10 3
1&
0)
b101 >
b1 4
b100 $
b100 7
b100 8
1+
#1020000
0+
#1025000
0&
1)
b1 3
b10 4
b101 $
b101 7
b101 8
1+
#1030000
0+
#1035000
b10 3
1&
0)
b110 >
b1 4
b110 $
b110 7
b110 8
1+
#1040000
0+
#1045000
0&
1)
b1 3
b10 4
b111 $
b111 7
b111 8
1+
#1050000
0+
#1055000
b10 3
1&
0)
b111 >
b1 4
b1000 $
b1000 7
b1000 8
1+
#1060000
0+
#1065000
0.
b10 E
0&
1)
b1 3
b10 4
b1001 $
b1001 7
b1001 8
1+
#1070000
0+
#1075000
b10 3
1&
0)
b1000 >
b1 4
b1010 $
b1010 7
b1010 8
1+
#1080000
0+
#1085000
0&
1)
b1 3
b10 4
b1011 $
b1011 7
b1011 8
1+
#1090000
0+
#1095000
b10 3
1&
0)
b1001 >
b1 4
b1100 $
b1100 7
b1100 8
1+
#1100000
0+
#1105000
0&
1)
b1 3
b10 4
b1101 $
b1101 7
b1101 8
1+
#1110000
0+
#1115000
b10 3
1&
0)
b1010 >
b1 4
b1110 $
b1110 7
b1110 8
1+
#1120000
0+
#1125000
0&
1)
b1 3
b10 4
b1111 $
b1111 7
b1111 8
1+
#1130000
0+
#1135000
b10 3
1&
0)
b1011 >
b1 4
b10000 $
b10000 7
b10000 8
1+
#1140000
0+
#1145000
0&
1)
b1 3
b10 4
b10001 $
b10001 7
b10001 8
1+
#1150000
0+
#1155000
b10 3
1&
0)
b1100 >
b1 4
b10010 $
b10010 7
b10010 8
1+
#1160000
0+
#1165000
0&
1)
b1 3
b10 4
b10011 $
b10011 7
b10011 8
1+
#1170000
0+
#1175000
b10 3
1&
0)
b1101 >
b1 4
b10100 $
b10100 7
b10100 8
1+
#1180000
0+
#1185000
0&
1)
b1 3
b10 4
b10101 $
b10101 7
b10101 8
1+
#1190000
0+
#1195000
b10 3
1&
0)
b1110 >
b1 4
b10110 $
b10110 7
b10110 8
1+
#1200000
0+
#1205000
0&
1)
b1 3
b10 4
b10111 $
b10111 7
b10111 8
1+
#1210000
0+
#1215000
b10 3
1&
0)
b1111 >
b1 4
b11000 $
b11000 7
b11000 8
1+
#1220000
0+
#1225000
0&
1)
b1 3
b10 4
b11001 $
b11001 7
b11001 8
1+
#1230000
0+
#1235000
b10 3
1&
0)
b10xxxxx C
b11 ?
b0 >
b1 4
b11010 $
b11010 7
b11010 8
1+
#1240000
0+
#1245000
0&
1)
b1 3
b10 4
b11011 $
b11011 7
b11011 8
1+
#1250000
0+
#1255000
b10 3
1&
0)
b1 >
b1 4
b11100 $
b11100 7
b11100 8
1+
#1260000
0+
#1265000
0&
1)
b1 3
b10 4
b11101 $
b11101 7
b11101 8
1+
#1270000
0+
#1275000
b10 3
1&
0)
b10 >
b1 4
b11110 $
b11110 7
b11110 8
1+
#1280000
0+
#1285000
0&
1(
1)
1'
b1 3
1%
b10 4
b11111 $
b11111 7
b11111 8
1+
#1290000
0+
#1295000
b10 3
1&
0(
0)
0'
0%
b11 >
b1 4
b0 $
b0 7
b0 8
1+
#1300000
0+
#1305000
0&
1)
b1 3
b10 4
b1 $
b1 7
b1 8
1+
#1310000
0+
#1315000
b10 3
1&
0)
b100 >
b1 4
b10 $
b10 7
b10 8
1+
#1320000
0+
#1325000
0&
1)
b1 3
b10 4
b11 $
b11 7
b11 8
1+
#1330000
0+
#1335000
b10 3
1&
0)
b101 >
b1 4
b100 $
b100 7
b100 8
1+
#1340000
0+
#1345000
0&
1)
b1 3
b10 4
b101 $
b101 7
b101 8
1+
#1350000
0+
#1355000
b10 3
1&
0)
b110 >
b1 4
b110 $
b110 7
b110 8
1+
#1360000
0+
#1365000
0&
1)
b1 3
b10 4
b111 $
b111 7
b111 8
1+
#1370000
0+
#1375000
b10 3
1&
0)
b111 >
b1 4
b1000 $
b1000 7
b1000 8
1+
#1380000
0+
#1385000
1.
b11 E
0&
1)
b1 3
b10 4
b1001 $
b1001 7
b1001 8
1+
#1390000
0+
#1395000
b10 3
1&
0)
b1000 >
b1 4
b1010 $
b1010 7
b1010 8
1+
#1400000
0+
#1405000
0&
1)
b1 3
b10 4
b1011 $
b1011 7
b1011 8
1+
#1410000
0+
#1415000
b10 3
1&
0)
b1001 >
b1 4
b1100 $
b1100 7
b1100 8
1+
#1420000
0+
#1425000
0&
1)
b1 3
b10 4
b1101 $
b1101 7
b1101 8
1+
#1430000
0+
#1435000
b10 3
1&
0)
b1010 >
b1 4
b1110 $
b1110 7
b1110 8
1+
#1440000
0+
#1445000
0&
1)
b1 3
b10 4
b1111 $
b1111 7
b1111 8
1+
#1450000
0+
#1455000
b10 3
1&
0)
b1011 >
b1 4
b10000 $
b10000 7
b10000 8
1+
#1460000
0+
#1465000
0&
1)
b1 3
b10 4
b10001 $
b10001 7
b10001 8
1+
#1470000
0+
#1475000
b10 3
1&
0)
b1100 >
b1 4
b10010 $
b10010 7
b10010 8
1+
#1480000
0+
#1485000
0&
1)
b1 3
b10 4
b10011 $
b10011 7
b10011 8
1+
#1490000
0+
#1495000
b10 3
1&
0)
b1101 >
b1 4
b10100 $
b10100 7
b10100 8
1+
#1500000
0+
#1505000
0&
1)
b1 3
b10 4
b10101 $
b10101 7
b10101 8
1+
#1510000
0+
#1515000
b10 3
1&
0)
b1110 >
b1 4
b10110 $
b10110 7
b10110 8
1+
#1520000
0+
#1525000
0&
1)
b1 3
b10 4
b10111 $
b10111 7
b10111 8
1+
#1530000
0+
#1535000
b10 3
1&
0)
b1111 >
b1 4
b11000 $
b11000 7
b11000 8
1+
#1540000
0+
#1545000
0&
1)
b1 3
b10 4
b11001 $
b11001 7
b11001 8
1+
#1550000
0+
#1555000
b10 3
1&
0)
b1010xxxx C
b100 ?
b0 >
b1 4
b11010 $
b11010 7
b11010 8
1+
#1560000
0+
#1565000
0&
1)
b1 3
b10 4
b11011 $
b11011 7
b11011 8
1+
#1570000
0+
#1575000
b10 3
1&
0)
b1 >
b1 4
b11100 $
b11100 7
b11100 8
1+
#1580000
0+
#1585000
0&
1)
b1 3
b10 4
b11101 $
b11101 7
b11101 8
1+
#1590000
0+
#1595000
b10 3
1&
0)
b10 >
b1 4
b11110 $
b11110 7
b11110 8
1+
#1600000
0+
#1605000
0&
1(
1)
1'
b1 3
1%
b10 4
b11111 $
b11111 7
b11111 8
1+
#1610000
0+
#1615000
b10 3
1&
0(
0)
0'
0%
b11 >
b1 4
b0 $
b0 7
b0 8
1+
#1620000
0+
#1625000
0&
1)
b1 3
b10 4
b1 $
b1 7
b1 8
1+
#1630000
0+
#1635000
b10 3
1&
0)
b100 >
b1 4
b10 $
b10 7
b10 8
1+
#1640000
0+
#1645000
0&
1)
b1 3
b10 4
b11 $
b11 7
b11 8
1+
#1650000
0+
#1655000
b10 3
1&
0)
b101 >
b1 4
b100 $
b100 7
b100 8
1+
#1660000
0+
#1665000
0&
1)
b1 3
b10 4
b101 $
b101 7
b101 8
1+
#1670000
0+
#1675000
b10 3
1&
0)
b110 >
b1 4
b110 $
b110 7
b110 8
1+
#1680000
0+
#1685000
0&
1)
b1 3
b10 4
b111 $
b111 7
b111 8
1+
#1690000
0+
#1695000
b10 3
1&
0)
b111 >
b1 4
b1000 $
b1000 7
b1000 8
1+
#1700000
0+
#1705000
0.
b100 E
0&
1)
b1 3
b10 4
b1001 $
b1001 7
b1001 8
1+
#1710000
0+
#1715000
b10 3
1&
0)
b1000 >
b1 4
b1010 $
b1010 7
b1010 8
1+
#1720000
0+
#1725000
0&
1)
b1 3
b10 4
b1011 $
b1011 7
b1011 8
1+
#1730000
0+
#1735000
b10 3
1&
0)
b1001 >
b1 4
b1100 $
b1100 7
b1100 8
1+
#1740000
0+
#1745000
0&
1)
b1 3
b10 4
b1101 $
b1101 7
b1101 8
1+
#1750000
0+
#1755000
b10 3
1&
0)
b1010 >
b1 4
b1110 $
b1110 7
b1110 8
1+
#1760000
0+
#1765000
0&
1)
b1 3
b10 4
b1111 $
b1111 7
b1111 8
1+
#1770000
0+
#1775000
b10 3
1&
0)
b1011 >
b1 4
b10000 $
b10000 7
b10000 8
1+
#1780000
0+
#1785000
0&
1)
b1 3
b10 4
b10001 $
b10001 7
b10001 8
1+
#1790000
0+
#1795000
b10 3
1&
0)
b1100 >
b1 4
b10010 $
b10010 7
b10010 8
1+
#1800000
0+
#1805000
0&
1)
b1 3
b10 4
b10011 $
b10011 7
b10011 8
1+
#1810000
0+
#1815000
b10 3
1&
0)
b1101 >
b1 4
b10100 $
b10100 7
b10100 8
1+
#1820000
0+
#1825000
0&
1)
b1 3
b10 4
b10101 $
b10101 7
b10101 8
1+
#1830000
0+
#1835000
b10 3
1&
0)
b1110 >
b1 4
b10110 $
b10110 7
b10110 8
1+
#1840000
0+
#1845000
0&
1)
b1 3
b10 4
b10111 $
b10111 7
b10111 8
1+
#1850000
0+
#1855000
b10 3
1&
0)
b1111 >
b1 4
b11000 $
b11000 7
b11000 8
1+
#1860000
0+
#1865000
0&
1)
b1 3
b10 4
b11001 $
b11001 7
b11001 8
1+
#1870000
0+
#1875000
b10 3
1&
0)
b1010xxx C
b101 ?
b0 >
b1 4
b11010 $
b11010 7
b11010 8
1+
#1880000
0+
#1885000
0&
1)
b1 3
b10 4
b11011 $
b11011 7
b11011 8
1+
#1890000
0+
#1895000
b10 3
1&
0)
b1 >
b1 4
b11100 $
b11100 7
b11100 8
1+
#1900000
0+
#1905000
0&
1)
b1 3
b10 4
b11101 $
b11101 7
b11101 8
1+
#1910000
0+
#1915000
b10 3
1&
0)
b10 >
b1 4
b11110 $
b11110 7
b11110 8
1+
#1920000
0+
#1925000
0&
1(
1)
1'
b1 3
1%
b10 4
b11111 $
b11111 7
b11111 8
1+
#1930000
0+
