Rx_/uart_rx.v
module uart_rx(
    input wire clk,
    input wire rst_n,
    input wire en,
    input wire rx_line,
    input wire baud_tick_16x,

    output reg rx_busy,
    output reg rx_done,
    output reg [7:0] data_received

);
reg [2:0] nstate, pstate;
reg [3:0] bit_count;
reg [3:0] baud_count;
reg [7:0] rx_shift_reg;

parameter [2:0] IDLE          = 3'b000,
                Enable        = 3'b001,
                Conf_rsv      = 3'b010,
                Receiving    = 3'b011,
                Receive_done  = 3'b100;

always @(*) begin: NSEQL //Non Sequential Logic
    begin:NSL //Next State Logic 
        case (pstate)
            IDLE: nstate = en ? Enable : IDLE;
            
            Enable: nstate = (!rx_line) ? Conf_rsv : Enable;  

            Conf_rsv: nstate = (baud_count == 4'd7) ? ((!rx_line) ? Receiving : Enable) : Conf_rsv;

            Receiving: nstate = (bit_count == 4'd8) ? Receive_done : Receiving;

            Receive_done: nstate = (!rx_line) ? Conf_rsv : Receive_done;

            default: nstate = IDLE;
        endcase
    end//end NSL

    begin: OL // Output logic
        case (pstate)
            IDLE: begin
                rx_busy = 1'b0;
                rx_done = 1'b0;
                data_received = 8'b0; // reset data received
                bit_count = 3'b0; // reset bit count
                baud_count = 4'b0; // reset baud count
            end 

            Enable: begin
                rx_busy = 1'b0;
                rx_done = 1'b0;
                data_received = 8'b0; // reset data received
                bit_count = 3'b0; // reset bit count
                baud_count = 4'b0; // reset baud count
            end

            Conf_rsv: begin 
                rx_busy = 1'b0;
                rx_done = 1'b0;
                //data_received = 8'b0;
                bit_count = 3'b0;
                if(baud_count >= 4'd7) begin 
                    baud_count = 4'b0;
                end
            end

            Receiving: begin 
                rx_busy = 1'b1;
                rx_done = 1'b0;
                data_received = 8'b0;
            end

            Receive_done: begin 
                rx_busy = 1'b0;
                rx_done = 1'b1;
                data_received = rx_shift_reg; // output the received data
                bit_count = 3'b0; // reset bit count
                baud_count = 4'b0; // reset baud count
            end
              
            default: begin 
                rx_busy <= 1'b0;
                rx_done <= 1'b0;
                data_received <= 8'b0; // reset data received
                bit_count <= 3'b0; // reset bit count
                baud_count <= 4'b0; // reset baud count
            end 
        endcase
    end//end OL
end //end NSEQL

always @(posedge clk, negedge rst_n) begin: SL // sequential logic
    if (!rst_n) begin
        pstate <= IDLE;
    end else begin
        if(pstate == Conf_rsv && baud_tick_16x) begin 
            baud_count <= baud_count + 1'b1;
        end
        if(pstate == Receiving && baud_tick_16x) begin 
            baud_count <= baud_count + 1'b1;
            if (baud_count == 4'd15) begin 
                baud_count <= 4'b0;
                bit_count <= bit_count + 1'b1;
                rx_shift_reg <= {rx_line, rx_shift_reg[7:1]};
            end
        end

        pstate <= nstate;
    end
end //end SL

endmodule

uart_tx.v
module uart_tx (
    input wire clk, 
    input wire rst_n,
    input wire en,
    input wire start_tx,
    input wire [7:0] data_in,
    input wire baud_tick_1x,

    output reg tx_busy,
    output reg tx_done,
    output reg tx_line
);

reg [2:0] nstate, pstate;
reg [9:0] tx_shift_reg;
reg [3:0] bit_count;

parameter [2:0]     IDLE         = 3'b000,
                    Enable       = 3'b001,
                    Make_pkt     = 3'b010,
                    sending      = 3'b011,
                    send_done    = 3'b100;

always @(*) begin: NSEQL // Non Sequential Logic
    begin: NSL // Next state Logic
        case(pstate) 
            IDLE    : nstate = en ? Enable : IDLE;

            Enable  : nstate = start_tx ? Make_pkt : Enable;

            Make_pkt: nstate = (baud_tick_1x)? sending : Make_pkt;

            sending : nstate = (bit_count >= 4'd10) ? send_done : sending;

            send_done: nstate = start_tx ? Make_pkt : send_done;

            default : nstate = IDLE;

        endcase

    end

    begin: OL // Output Logic  
        case(pstate) 
            IDLE    : 
                begin 
                    tx_busy <= 1'b0;
                    tx_done <= 1'b0;
                    tx_line <= 1'b1; // idle state of UART line is high
                    bit_count <= 4'b0; // reset bit count             
                end

            Enable  : 
                begin 
                    tx_busy <= 1'b0;
                    tx_done <= 1'b0;
                    tx_line <= 1'b1; // idle state of UART line is high     
                    bit_count <= 4'b0; // reset bit count         
                end

            Make_pkt:
                begin 
                    tx_busy <= 1'b1;
                    tx_done <= 1'b0;
                    tx_line <= 1'b1; // start bit is low
                    tx_shift_reg <= {1'b1, data_in, 1'b0}; // add stop bit and start bit
                    bit_count <= 4'b0; // reset bit count
                end

            sending : 
                begin 
                    tx_busy <= 1'b1;
                    tx_done <= 1'b0;
                    if(bit_count >= 4'd10)begin 
                        tx_line <= 1'b1;;
                    end else begin 
                        tx_line <= tx_shift_reg[0];
                    end
                    
                end

            send_done: 
                begin 
                    tx_busy <= 1'b0;
                    tx_done <= 1'b1;
                    tx_line <= 1'b1; // stop bit is high
                    bit_count <= 4'b0; // reset bit count
                end

            default : 
                begin 
                    tx_busy <= 1'bx;
                    tx_done <= 1'bx;
                    tx_line <= 1'bx; // idle state of UART line is high
                end
        endcase
    end

end

always @(posedge clk, negedge rst_n) begin : SEQL // sequential Logic
    if(~rst_n) begin 
        pstate <= IDLE;
        bit_count <= 4'b0;
        tx_shift_reg <= 10'b0;
    end
    else begin
        if(pstate == sending && baud_tick_1x) begin
            tx_shift_reg <= tx_shift_reg >>1; // shift right
            bit_count <= bit_count + 1'b1; // increment bit count
        end
        pstate <= nstate;
        
    end
end

endmodule

baud_gen.v
module baud_gen (
    input wire clk, 
    input wire rst_n,
    input wire cnt_1x,
    input wire cnt_16x,

    output reg clr,
    output reg baud_tick_1x,
    output reg baud_tick_16x

);

reg [1:0] nstate, pstate;

parameter [1:0]     IDLE         = 2'b00,
                    running      = 2'b01,
                    tick_16x     = 2'b10,
                    tick_1x      = 2'b11;

always @(*) begin: NSEQL // Non Sequential Logic
    begin: NSL // Next state Logic
        case(pstate) 
            IDLE    : nstate = (rst_n ? running : IDLE);
        
            running : nstate = (cnt_1x  ? tick_1x  : (cnt_16x ? tick_16x : running));
            
            tick_16x: nstate = running;

            tick_1x : nstate = running;

            default : nstate = IDLE;
            
        endcase

    end

    begin: OL // Output Logic  
        case(pstate) 
            IDLE    : begin 
                        clr = 1'b1;
                        baud_tick_16x = 1'b0;
                        baud_tick_1x = 1'b0;
            end
            running : begin 
                        clr = 1'b0;
                        baud_tick_16x = 1'b0;
                        baud_tick_1x = 1'b0;
            end
            tick_16x: begin 
                        clr = cnt_1x ? 1'b1 : 1'b0;
                        baud_tick_16x = 1'b1;
                        baud_tick_1x  = cnt_1x ? 1'b1 : 1'b0;
            end
            tick_1x : begin 
                        clr = 1'b1;
                        baud_tick_16x = 1'b1;
                        baud_tick_1x  = 1'b1;
            end
            default : begin 

            end
        endcase
    end

end

always @(posedge clk, negedge rst_n) begin : SEQL // sequential Logic
    if(~rst_n) begin 
        pstate <= IDLE;
    end
    else begin 
        pstate <= nstate;
    end
end

endmodule

count_comp/comparator.v
module comparator (
    input wire [15:0] count,
    input wire [15:0] baud_div,

    output wire cnt_16x,
    output wire cnt_1x
);
    wire[15:0] step_16x = baud_div >> 4;
    //reg [3:0] baud_count;
    assign cnt_1x = (count == baud_div-1) ? 1'b1 : 1'b0;
    assign cnt_16x = ((step_16x !=0) && ((count % step_16x)==0))? 1'b1 : 1'b0;

endmodule

count_comp/counter.v
module counter (
    input wire clk,
    input wire rst_n,
    input wire clr,

    output reg [15:0] count
);

always @(posedge clk, negedge rst_n) begin
    if(~rst_n) begin 
        count <= 16'd0;
    end
    else begin 
        count <= clr ? 16'd0 : count + 1;
    end
    
end
    
endmodule

Top_/top.v
module top(
    input wire clk,
    input wire rst_n,
    input wire en_tx,
    input wire en_rx,

    input wire [15:0] baud_div,

    input wire start_tx,
    input wire [7:0] data_in,

    input wire rx_line,

    output wire tx_busy,
    output wire tx_done,
    output wire tx_line,

    // to send data internnaly, we need 16x out
    output wire baud_tick_16x,

    output wire rx_busy,
    output wire rx_done,
    output wire [7:0] data_received


);

wire clr,
     cnt_16x,
     cnt_1x,
     //baud_tick_16x,
     baud_tick_1x;

wire [15:0] count;

counter uut_counter (
    .clk(clk),
    .rst_n(rst_n),
    .clr(clr),
    .count(count)
);

comparator uut_comparator(
    .count(count),
    .baud_div(baud_div),
    .cnt_16x(cnt_16x),
    .cnt_1x(cnt_1x)
);

baud_gen uut_baud_gen(
    .clk(clk), 
    .rst_n(rst_n),
    .cnt_1x(cnt_1x),
    .cnt_16x(cnt_16x),

    .clr(clr),
    .baud_tick_1x(baud_tick_1x),
    .baud_tick_16x(baud_tick_16x)
);

uart_tx uut_uart_tx(
    .clk(clk), 
    .rst_n(rst_n),
    .en(en_tx),
    .start_tx(start_tx),
    .data_in(data_in),
    .baud_tick_1x(baud_tick_1x),
    .tx_busy(tx_busy),
    .tx_done(tx_done),
    .tx_line(tx_line)
);

uart_rx uut_uart_rx(
    .clk(clk),
    .rst_n(rst_n),
    .en(en_rx),
    .rx_line(rx_line),
    .baud_tick_16x(baud_tick_16x),
    .rx_busy(rx_busy),
    .rx_done(rx_done),
    .data_received(data_received)
);


endmodule

Top_/tb_top.v
`timescale 1ns/1ps

module tb_top;

    reg clk=0;
    reg rst_n;
    reg en_tx;
    reg en_rx;

    reg [15:0] baud_div;

    reg start_tx;
    reg [7:0] data_in;

    reg rx_line;

    wire tx_busy;
    wire tx_done;
    wire tx_line;

    wire rx_busy;
    wire rx_done;
    wire [7:0] data_received;

    wire baud_tick_16x;

top uut_top(
    .clk(clk),
    .rst_n(rst_n),
    .en_tx(en_tx),
    .en_rx(en_rx),

    .baud_div(baud_div),

    .start_tx(start_tx),
    .data_in(data_in),

    .rx_line(rx_line),

    .tx_busy(tx_busy),
    .tx_done(tx_done),
    .tx_line(tx_line),
    .rx_busy(rx_busy),

    .rx_done(rx_done),
    .data_received(data_received),
    .baud_tick_16x(baud_tick_16x)
);

always #5 clk = ~clk;

task send_byte(input [7:0] byte);
    integer i;
    begin 
        //Start bit
        rx_line = 1'b0;
        repeat(16)@(posedge baud_tick_16x);

        //Sending data
        for( i =0; i<8; i++)begin 
            rx_line = byte[i];
            repeat(16)@(posedge baud_tick_16x);
        end

        //sending stop bit

        rx_line =  1'b1;
        repeat(16)@(posedge baud_tick_16x);
    end
endtask

initial begin
    $dumpfile("tb_top.vcd");
    $dumpvars(0,tb_top);

    rst_n <= 1'b0;
    en_tx <= 0 ;
    en_rx <= 0;
    baud_div <= 16'd32;
    start_tx <= 0;
    data_in <= 0;
    rx_line <= 1;
    @(negedge clk);

    rst_n <= 1'b1;
    repeat(3)@(negedge clk);

    en_tx <= 1'b1;
    @(negedge clk);

    //sending data AA
    data_in <= 8'hAA;
    start_tx <= 1'b1;
    repeat(1)@(negedge clk);
    start_tx <= 1'b0;
    repeat(364)@(negedge clk);

    //sending data 
    data_in <= 8'b11001100;
    start_tx =1;
    @(negedge clk);
    start_tx =0;
    repeat(364)@(negedge clk);


    en_rx = 1;
    repeat(2)@(negedge clk);

    //receiveing data AB
    send_byte(8'hAB);
    repeat(170)@(posedge clk);
    
    //receiving data BD
    send_byte(8'hBD);
    repeat(170)@(posedge clk);

    //sending and receing same time
    data_in <= 8'b10101010;
    start_tx <=1;
    send_byte(8'hA9);
    @(negedge clk);
    start_tx =0;
    repeat(364)@(negedge clk);


    $finish;

end



endmodule

tb_top.vcd
$date
	Tue Jul 08 00:09:03 2025
$end
$version
	Icarus Verilog
$end
$timescale
	1ps
$end
$scope module tb_top $end
$var wire 1 ! tx_line $end
$var wire 1 " tx_done $end
$var wire 1 # tx_busy $end
$var wire 1 $ rx_done $end
$var wire 1 % rx_busy $end
$var wire 8 & data_received [7:0] $end
$var wire 1 ' baud_tick_16x $end
$var reg 16 ( baud_div [15:0] $end
$var reg 1 ) clk $end
$var reg 8 * data_in [7:0] $end
$var reg 1 + en_rx $end
$var reg 1 , en_tx $end
$var reg 1 - rst_n $end
$var reg 1 . rx_line $end
$var reg 1 / start_tx $end
$scope module uut_top $end
$var wire 16 0 baud_div [15:0] $end
$var wire 1 ) clk $end
$var wire 8 1 data_in [7:0] $end
$var wire 1 + en_rx $end
$var wire 1 , en_tx $end
$var wire 1 - rst_n $end
$var wire 1 . rx_line $end
$var wire 1 / start_tx $end
$var wire 1 ! tx_line $end
$var wire 1 " tx_done $end
$var wire 1 # tx_busy $end
$var wire 1 $ rx_done $end
$var wire 1 % rx_busy $end
$var wire 8 2 data_received [7:0] $end
$var wire 16 3 count [15:0] $end
$var wire 1 4 cnt_1x $end
$var wire 1 5 cnt_16x $end
$var wire 1 6 clr $end
$var wire 1 7 baud_tick_1x $end
$var wire 1 ' baud_tick_16x $end
$scope module uut_baud_gen $end
$var wire 1 ) clk $end
$var wire 1 - rst_n $end
$var wire 1 4 cnt_1x $end
$var wire 1 5 cnt_16x $end
$var parameter 2 8 IDLE $end
$var parameter 2 9 running $end
$var parameter 2 : tick_16x $end
$var parameter 2 ; tick_1x $end
$var reg 1 ' baud_tick_16x $end
$var reg 1 7 baud_tick_1x $end
$var reg 1 6 clr $end
$var reg 2 < nstate [1:0] $end
$var reg 2 = pstate [1:0] $end
$scope begin NSEQL $end
$scope begin NSL $end
$upscope $end
$scope begin OL $end
$upscope $end
$upscope $end
$scope begin SEQL $end
$upscope $end
$upscope $end
$scope module uut_comparator $end
$var wire 16 > baud_div [15:0] $end
$var wire 16 ? step_16x [15:0] $end
$var wire 16 @ count [15:0] $end
$var wire 1 4 cnt_1x $end
$var wire 1 5 cnt_16x $end
$upscope $end
$scope module uut_counter $end
$var wire 1 ) clk $end
$var wire 1 6 clr $end
$var wire 1 - rst_n $end
$var reg 16 A count [15:0] $end
$upscope $end
$scope module uut_uart_rx $end
$var wire 1 ' baud_tick_16x $end
$var wire 1 ) clk $end
$var wire 1 + en $end
$var wire 1 - rst_n $end
$var wire 1 . rx_line $end
$var parameter 3 B Conf_rsv $end
$var parameter 3 C Enable $end
$var parameter 3 D IDLE $end
$var parameter 3 E Receive_done $end
$var parameter 3 F Receiving $end
$var reg 4 G baud_count [3:0] $end
$var reg 4 H bit_count [3:0] $end
$var reg 8 I data_received [7:0] $end
$var reg 3 J nstate [2:0] $end
$var reg 3 K pstate [2:0] $end
$var reg 1 % rx_busy $end
$var reg 1 $ rx_done $end
$var reg 8 L rx_shift_reg [7:0] $end
$scope begin NSEQL $end
$scope begin NSL $end
$upscope $end
$scope begin OL $end
$upscope $end
$upscope $end
$scope begin SL $end
$upscope $end
$upscope $end
$scope module uut_uart_tx $end
$var wire 1 7 baud_tick_1x $end
$var wire 1 ) clk $end
$var wire 8 M data_in [7:0] $end
$var wire 1 , en $end
$var wire 1 - rst_n $end
$var wire 1 / start_tx $end
$var parameter 3 N Enable $end
$var parameter 3 O IDLE $end
$var parameter 3 P Make_pkt $end
$var parameter 3 Q send_done $end
$var parameter 3 R sending $end
$var reg 4 S bit_count [3:0] $end
$var reg 3 T nstate [2:0] $end
$var reg 3 U pstate [2:0] $end
$var reg 1 # tx_busy $end
$var reg 1 " tx_done $end
$var reg 1 ! tx_line $end
$var reg 10 V tx_shift_reg [9:0] $end
$scope begin NSEQL $end
$scope begin NSL $end
$upscope $end
$scope begin OL $end
$upscope $end
$upscope $end
$scope begin SEQL $end
$upscope $end
$upscope $end
$upscope $end
$scope task send_byte $end
$var reg 8 W byte [7:0] $end
$var integer 32 X i [31:0] $end
$upscope $end
$upscope $end
$enddefinitions $end
$comment Show the parameter values. $end
$dumpall
b11 R
b100 Q
b10 P
b0 O
b1 N
b11 F
b100 E
b0 D
b1 C
b10 B
b11 ;
b10 :
b1 9
b0 8
$end
#0
$dumpvars
bx X
bx W
b0 V
b0 U
b0 T
b0 S
b0 M
bx L
b0 K
b0 J
b0 I
b0 H
b0 G
b0 A
b0 @
b10 ?
b100000 >
b0 =
b0 <
07
16
15
04
b0 3
b0 2
b0 1
b100000 0
0/
1.
0-
0,
0+
b0 *
0)
b100000 (
0'
b0 &
0%
0$
0#
0"
1!
$end
#5000
1)
#10000
b1 <
1-
0)
#15000
06
b10 <
b1 =
1)
#20000
0)
#25000
05
1'
b1 <
b10 =
b1 3
b1 @
b1 A
1)
#30000
0)
#35000
b10 <
15
0'
b1 =
b10 3
b10 @
b10 A
1)
#40000
b1 T
1,
0)
#45000
05
1'
b1 <
b1 U
b10 =
b11 3
b11 @
b11 A
1)
#50000
b10 T
1/
b10101010 *
b10101010 1
b10101010 M
0)
#55000
b1101010100 V
1#
b10 <
15
0'
b10 U
b1 =
b100 3
b100 @
b100 A
1)
#60000
0/
0)
#65000
05
1'
b1 <
b10 =
b101 3
b101 @
b101 A
1)
#70000
0)
#75000
b10 <
15
0'
b1 =
b110 3
b110 @
b110 A
1)
#80000
0)
#85000
05
1'
b1 <
b10 =
b111 3
b111 @
b111 A
1)
#90000
0)
#95000
b10 <
15
0'
b1 =
b1000 3
b1000 @
b1000 A
1)
#100000
0)
#105000
05
1'
b1 <
b10 =
b1001 3
b1001 @
b1001 A
1)
#110000
0)
#115000
b10 <
15
0'
b1 =
b1010 3
b1010 @
b1010 A
1)
#120000
0)
#125000
05
1'
b1 <
b10 =
b1011 3
b1011 @
b1011 A
1)
#130000
0)
#135000
b10 <
15
0'
b1 =
b1100 3
b1100 @
b1100 A
1)
#140000
0)
#145000
05
1'
b1 <
b10 =
b1101 3
b1101 @
b1101 A
1)
#150000
0)
#155000
b10 <
15
0'
b1 =
b1110 3
b1110 @
b1110 A
1)
#160000
0)
#165000
05
1'
b1 <
b10 =
b1111 3
b1111 @
b1111 A
1)
#170000
0)
#175000
b10 <
15
0'
b1 =
b10000 3
b10000 @
b10000 A
1)
#180000
0)
#185000
05
1'
b1 <
b10 =
b10001 3
b10001 @
b10001 A
1)
#190000
0)
#195000
b10 <
15
0'
b1 =
b10010 3
b10010 @
b10010 A
1)
#200000
0)
#205000
05
1'
b1 <
b10 =
b10011 3
b10011 @
b10011 A
1)
#210000
0)
#215000
b10 <
15
0'
b1 =
b10100 3
b10100 @
b10100 A
1)
#220000
0)
#225000
05
1'
b1 <
b10 =
b10101 3
b10101 @
b10101 A
1)
#230000
0)
#235000
b10 <
15
0'
b1 =
b10110 3
b10110 @
b10110 A
1)
#240000
0)
#245000
05
1'
b1 <
b10 =
b10111 3
b10111 @
b10111 A
1)
#250000
0)
#255000
b10 <
15
0'
b1 =
b11000 3
b11000 @
b11000 A
1)
#260000
0)
#265000
05
1'
b1 <
b10 =
b11001 3
b11001 @
b11001 A
1)
#270000
0)
#275000
b10 <
15
0'
b1 =
b11010 3
b11010 @
b11010 A
1)
#280000
0)
#285000
05
1'
b1 <
b10 =
b11011 3
b11011 @
b11011 A
1)
#290000
0)
#295000
b10 <
15
0'
b1 =
b11100 3
b11100 @
b11100 A
1)
#300000
0)
#305000
05
1'
b1 <
b10 =
b11101 3
b11101 @
b11101 A
1)
#310000
0)
#315000
b10 <
15
0'
b1 =
b11110 3
b11110 @
b11110 A
1)
#320000
0)
#325000
b11 T
05
17
1'
16
b1 <
14
b10 =
b11111 3
b11111 @
b11111 A
1)
#330000
0)
#335000
0!
b10 <
15
07
0'
06
04
b11 U
b1 =
b0 3
b0 @
b0 A
1)
#340000
0)
#345000
05
1'
b1 <
b10 =
b1 3
b1 @
b1 A
1)
#350000
0)
#355000
b10 <
15
0'
b1 =
b10 3
b10 @
b10 A
1)
#360000
0)
#365000
05
1'
b1 <
b10 =
b11 3
b11 @
b11 A
1)
#370000
0)
#375000
b10 <
15
0'
b1 =
b100 3
b100 @
b100 A
1)
#380000
0)
#385000
05
1'
b1 <
b10 =
b101 3
b101 @
b101 A
1)
#390000
0)
#395000
b10 <
15
0'
b1 =
b110 3
b110 @
b110 A
1)
#400000
0)
#405000
05
1'
b1 <
b10 =
b111 3
b111 @
b111 A
1)
#410000
0)
#415000
b10 <
15
0'
b1 =
b1000 3
b1000 @
b1000 A
1)
#420000
0)
#425000
05
1'
b1 <
b10 =
b1001 3
b1001 @
b1001 A
1)
#430000
0)
#435000
b10 <
15
0'
b1 =
b1010 3
b1010 @
b1010 A
1)
#440000
0)
#445000
05
1'
b1 <
b10 =
b1011 3
b1011 @
b1011 A
1)
#450000
0)
#455000
b10 <
15
0'
b1 =
b1100 3
b1100 @
b1100 A
1)
#460000
0)
#465000
05
1'
b1 <
b10 =
b1101 3
b1101 @
b1101 A
1)
#470000
0)
#475000
b10 <
15
0'
b1 =
b1110 3
b1110 @
b1110 A
1)
#480000
0)
#485000
05
1'
b1 <
b10 =
b1111 3
b1111 @
b1111 A
1)
#490000
0)
#495000
b10 <
15
0'
b1 =
b10000 3
b10000 @
b10000 A
1)
#500000
0)
#505000
05
1'
b1 <
b10 =
b10001 3
b10001 @
b10001 A
1)
#510000
0)
#515000
b10 <
15
0'
b1 =
b10010 3
b10010 @
b10010 A
1)
#520000
0)
#525000
05
1'
b1 <
b10 =
b10011 3
b10011 @
b10011 A
1)
#530000
0)
#535000
b10 <
15
0'
b1 =
b10100 3
b10100 @
b10100 A
1)
#540000
0)
#545000
05
1'
b1 <
b10 =
b10101 3
b10101 @
b10101 A
1)
#550000
0)
#555000
b10 <
15
0'
b1 =
b10110 3
b10110 @
b10110 A
1)
#560000
0)
#565000
05
1'
b1 <
b10 =
b10111 3
b10111 @
b10111 A
1)
#570000
0)
#575000
b10 <
15
0'
b1 =
b11000 3
b11000 @
b11000 A
1)
#580000
0)
#585000
05
1'
b1 <
b10 =
b11001 3
b11001 @
b11001 A
1)
#590000
0)
#595000
b10 <
15
0'
b1 =
b11010 3
b11010 @
b11010 A
1)
#600000
0)
#605000
05
1'
b1 <
b10 =
b11011 3
b11011 @
b11011 A
1)
#610000
0)
#615000
b10 <
15
0'
b1 =
b11100 3
b11100 @
b11100 A
1)
#620000
0)
#625000
05
1'
b1 <
b10 =
b11101 3
b11101 @
b11101 A
1)
#630000
0)
#635000
b10 <
15
0'
b1 =
b11110 3
b11110 @
b11110 A
1)
#640000
0)
#645000
05
17
1'
16
b1 <
14
b10 =
b11111 3
b11111 @
b11111 A
1)
#650000
0)
#655000
b10 <
15
07
0'
06
04
b1 S
b110101010 V
b1 =
b0 3
b0 @
b0 A
1)
#660000
0)
#665000
05
1'
b1 <
b10 =
b1 3
b1 @
b1 A
1)
#670000
0)
#675000
b10 <
15
0'
b1 =
b10 3
b10 @
b10 A
1)
#680000
0)
#685000
05
1'
b1 <
b10 =
b11 3
b11 @
b11 A
1)
#690000
0)
#695000
b10 <
15
0'
b1 =
b100 3
b100 @
b100 A
1)
#700000
0)
#705000
05
1'
b1 <
b10 =
b101 3
b101 @
b101 A
1)
#710000
0)
#715000
b10 <
15
0'
b1 =
b110 3
b110 @
b110 A
1)
#720000
0)
#725000
05
1'
b1 <
b10 =
b111 3
b111 @
b111 A
1)
#730000
0)
#735000
b10 <
15
0'
b1 =
b1000 3
b1000 @
b1000 A
1)
#740000
0)
#745000
05
1'
b1 <
b10 =
b1001 3
b1001 @
b1001 A
1)
#750000
0)
#755000
b10 <
15
0'
b1 =
b1010 3
b1010 @
b1010 A
1)
#760000
0)
#765000
05
1'
b1 <
b10 =
b1011 3
b1011 @
b1011 A
1)
#770000
0)
#775000
b10 <
15
0'
b1 =
b1100 3
b1100 @
b1100 A
1)
#780000
0)
#785000
05
1'
b1 <
b10 =
b1101 3
b1101 @
b1101 A
1)
#790000
0)
#795000
b10 <
15
0'
b1 =
b1110 3
b1110 @
b1110 A
1)
#800000
0)
#805000
05
1'
b1 <
b10 =
b1111 3
b1111 @
b1111 A
1)
#810000
0)
#815000
b10 <
15
0'
b1 =
b10000 3
b10000 @
b10000 A
1)
#820000
0)
#825000
05
1'
b1 <
b10 =
b10001 3
b10001 @
b10001 A
1)
#830000
0)
#835000
b10 <
15
0'
b1 =
b10010 3
b10010 @
b10010 A
1)
#840000
0)
#845000
05
1'
b1 <
b10 =
b10011 3
b10011 @
b10011 A
1)
#850000
0)
#855000
b10 <
15
0'
b1 =
b10100 3
b10100 @
b10100 A
1)
#860000
0)
#865000
05
1'
b1 <
b10 =
b10101 3
b10101 @
b10101 A
1)
#870000
0)
#875000
b10 <
15
0'
b1 =
b10110 3
b10110 @
b10110 A
1)
#880000
0)
#885000
05
1'
b1 <
b10 =
b10111 3
b10111 @
b10111 A
1)
#890000
0)
#895000
b10 <
15
0'
b1 =
b11000 3
b11000 @
b11000 A
1)
#900000
0)
#905000
05
1'
b1 <
b10 =
b11001 3
b11001 @
b11001 A
1)
#910000
0)
#915000
b10 <
15
0'
b1 =
b11010 3
b11010 @
b11010 A
1)
#920000
0)
#925000
05
1'
b1 <
b10 =
b11011 3
b11011 @
b11011 A
1)
#930000
0)
#935000
b10 <
15
0'
b1 =
b11100 3
b11100 @
b11100 A
1)
#940000
0)
#945000
05
1'
b1 <
b10 =
b11101 3
b11101 @
b11101 A
1)
#950000
0)
#955000
b10 <
15
0'
b1 =
b11110 3
b11110 @
b11110 A
1)
#960000
0)
#965000
05
17
1'
16
b1 <
14
b10 =
b11111 3
b11111 @
b11111 A
1)
#970000
0)
#975000
1!
b10 <
15
07
0'
06
04
b10 S
b11010101 V
b1 =
b0 3
b0 @
b0 A
1)
#980000
0)
#985000
05
1'
b1 <
b10 =
b1 3
b1 @
b1 A
1)
#990000
0)
#995000
b10 <
15
0'
b1 =
b10 3
b10 @
b10 A
1)
#1000000
0)
#1005000
05
1'
b1 <
b10 =
b11 3
b11 @
b11 A
1)
#1010000
0)
#1015000
b10 <
15
0'
b1 =
b100 3
b100 @
b100 A
1)
#1020000
0)
#1025000
05
1'
b1 <
b10 =
b101 3
b101 @
b101 A
1)
#1030000
0)
#1035000
b10 <
15
0'
b1 =
b110 3
b110 @
b110 A
1)
#1040000
0)
#1045000
05
1'
b1 <
b10 =
b111 3
b111 @
b111 A
1)
#1050000
0)
#1055000
b10 <
15
0'
b1 =
b1000 3
b1000 @
b1000 A
1)
#1060000
0)
#1065000
05
1'
b1 <
b10 =
b1001 3
b1001 @
b1001 A
1)
#1070000
0)
#1075000
b10 <
15
0'
b1 =
b1010 3
b1010 @
b1010 A
1)
#1080000
0)
#1085000
05
1'
b1 <
b10 =
b1011 3
b1011 @
b1011 A
1)
#1090000
0)
#1095000
b10 <
15
0'
b1 =
b1100 3
b1100 @
b1100 A
1)
#1100000
0)
#1105000
05
1'
b1 <
b10 =
b1101 3
b1101 @
b1101 A
1)
#1110000
0)
#1115000
b10 <
15
0'
b1 =
b1110 3
b1110 @
b1110 A
1)
#1120000
0)
#1125000
05
1'
b1 <
b10 =
b1111 3
b1111 @
b1111 A
1)
#1130000
0)
#1135000
b10 <
15
0'
b1 =
b10000 3
b10000 @
b10000 A
1)
#1140000
0)
#1145000
05
1'
b1 <
b10 =
b10001 3
b10001 @
b10001 A
1)
#1150000
0)
#1155000
b10 <
15
0'
b1 =
b10010 3
b10010 @
b10010 A
1)
#1160000
0)
#1165000
05
1'
b1 <
b10 =
b10011 3
b10011 @
b10011 A
1)
#1170000
0)
#1175000
b10 <
15
0'
b1 =
b10100 3
b10100 @
b10100 A
1)
#1180000
0)
#1185000
05
1'
b1 <
b10 =
b10101 3
b10101 @
b10101 A
1)
#1190000
0)
#1195000
b10 <
15
0'
b1 =
b10110 3
b10110 @
b10110 A
1)
#1200000
0)
#1205000
05
1'
b1 <
b10 =
b10111 3
b10111 @
b10111 A
1)
#1210000
0)
#1215000
b10 <
15
0'
b1 =
b11000 3
b11000 @
b11000 A
1)
#1220000
0)
#1225000
05
1'
b1 <
b10 =
b11001 3
b11001 @
b11001 A
1)
#1230000
0)
#1235000
b10 <
15
0'
b1 =
b11010 3
b11010 @
b11010 A
1)
#1240000
0)
#1245000
05
1'
b1 <
b10 =
b11011 3
b11011 @
b11011 A
1)
#1250000
0)
#1255000
b10 <
15
0'
b1 =
b11100 3
b11100 @
b11100 A
1)
#1260000
0)
#1265000
05
1'
b1 <
b10 =
b11101 3
b11101 @
b11101 A
1)
#1270000
0)
#1275000
b10 <
15
0'
b1 =
b11110 3
b11110 @
b11110 A
1)
#1280000
0)
#1285000
05
17
1'
16
b1 <
14
b10 =
b11111 3
b11111 @
b11111 A
1)
#1290000
0)
#1295000
0!
b10 <
15
07
0'
06
04
b11 S
b1101010 V
b1 =
b0 3
b0 @
b0 A
1)
#1300000
0)
#1305000
05
1'
b1 <
b10 =
b1 3
b1 @
b1 A
1)
#1310000
0)
#1315000
b10 <
15
0'
b1 =
b10 3
b10 @
b10 A
1)
#1320000
0)
#1325000
05
1'
b1 <
b10 =
b11 3
b11 @
b11 A
1)
#1330000
0)
#1335000
b10 <
15
0'
b1 =
b100 3
b100 @
b100 A
1)
#1340000
0)
#1345000
05
1'
b1 <
b10 =
b101 3
b101 @
b101 A
1)
#1350000
0)
#1355000
b10 <
15
0'
b1 =
b110 3
b110 @
b110 A
1)
#1360000
0)
#1365000
05
1'
b1 <
b10 =
b111 3
b111 @
b111 A
1)
#1370000
0)
#1375000
b10 <
15
0'
b1 =
b1000 3
b1000 @
b1000 A
1)
#1380000
0)
#1385000
05
1'
b1 <
b10 =
b1001 3
b1001 @
b1001 A
1)
#1390000
0)
#1395000
b10 <
15
0'
b1 =
b1010 3
b1010 @
b1010 A
1)
#1400000
0)
#1405000
05
1'
b1 <
b10 =
b1011 3
b1011 @
b1011 A
1)
#1410000
0)
#1415000
b10 <
15
0'
b1 =
b1100 3
b1100 @
b1100 A
1)
#1420000
0)
#1425000
05
1'
b1 <
b10 =
b1101 3
b1101 @
b1101 A
1)
#1430000
0)
#1435000
b10 <
15
0'
b1 =
b1110 3
b1110 @
b1110 A
1)
#1440000
0)
#1445000
05
1'
b1 <
b10 =
b1111 3
b1111 @
b1111 A
1)
#1450000
0)
#1455000
b10 <
15
0'
b1 =
b10000 3
b10000 @
b10000 A
1)
#1460000
0)
#1465000
05
1'
b1 <
b10 =
b10001 3
b10001 @
b10001 A
1)
#1470000
0)
#1475000
b10 <
15
0'
b1 =
b10010 3
b10010 @
b10010 A
1)
